weightedmodels/__init__.py
weightedmodels/core.py
weightedmodels-1.0.7.dist-info/METADATA
weightedmodels-1.0.7.dist-info/WHEEL
weightedmodels-1.0.7.dist-info/top_level.txt
weightedmodels-1.0.7.dist-info/RECORD
