Metadata-Version: 2.1
Name: weightedmodels
Version: 1.0.7
Home-page: https://github.com/AbdelRahmanYaghi/WeightedModels/edit/main/README.md
Author: AbdelRahman Yaghi
Author-email: abd20200355@std.psut.edu.jo
Keywords: Weighted models
Requires-Dist: scikit-learn
